simple_websocket/__init__.py
simple_websocket/aiows.py
simple_websocket/asgi.py
simple_websocket/errors.py
simple_websocket/ws.py
simple_websocket-1.0.0.dist-info/LICENSE
simple_websocket-1.0.0.dist-info/METADATA
simple_websocket-1.0.0.dist-info/WHEEL
simple_websocket-1.0.0.dist-info/top_level.txt
simple_websocket-1.0.0.dist-info/RECORD
