Metadata-Version: 2.1
Name: simple-websocket
Version: 1.0.0
Summary: Simple WebSocket server and client for Python
Home-page: https://github.com/miguelgrinberg/simple-websocket
Author: Miguel Grinberg
Author-email: miguel.grinberg@gmail.com
Project-URL: Bug Tracker, https://github.com/miguelgrinberg/simple-websocket/issues
Classifier: Environment :: Web Environment
Classifier: Intended Audience :: Developers
Classifier: Programming Language :: Python :: 3
Classifier: License :: OSI Approved :: MIT License
Classifier: Operating System :: OS Independent
Requires-Python: >=3.6
License-File: LICENSE
Requires-Dist: wsproto
Provides-Extra: docs
Requires-Dist: sphinx; extra == "docs"
